[
  {
    "IdReference": null,
    "DataAreaId": "2",
    "C_referencia": "9271513",
    "ItemId": "PF11810119",
    "ItemName": "VESTIDO SIAM",
    "C_proveedor": "1",
    "Dimension": "6",
    "CodLine": "0",
    "CodReference": null,
    "CodCategory": "26",
    "C_Subcategoria": "2",
    "CodSegmento": "11",
    "DivisionId": "81",
    "C_grupo_talla": "0",
    "ItemCollectionId": "325",
    "C_material": "0",
    "C_beneficio": "0",
    "C_clasificacion": "1",
    "Iva": "16",
    "HistoricPricePuch": "0,00",
    "Amount": "0,00",
    "HistoricPricePonderado": "20.951,00",
    "Unidad_empaque": "0",
    "CompositionId1": "",
    "Ptg_max_dscto": "70.0",
    "B_cambia_precio": "1",
    "Categoria": "P    ",
    "B_kit": "0",
    "B_explosion": "0",
    "B_promocion": "1",
    "Ubicacion": "0",
    "Und_medida": "1",
    "Dscto_vta": "70",
    "B_surtido": "1",
    "B_precio_max": "0",
    "Consumo": ".0",
    "Decimal1": "0",
    "Sw_serial": "0",
    "Sw_valida_max_dscto": "1",
    "Sw_Venta_Negativa": "1",
    "IdState": null
  },
  {
    "IdReference": null,
    "DataAreaId": "2",
    "C_referencia": "9271750",
    "ItemId": "PF11810123",
    "ItemName": "VESTIDO CORVINA",
    "C_proveedor": "1",
    "Dimension": "6",
    "CodLine": "0",
    "CodReference": null,
    "CodCategory": "26",
    "C_Subcategoria": "2",
    "CodSegmento": "11",
    "DivisionId": "81",
    "C_grupo_talla": "0",
    "ItemCollectionId": "325",
    "C_material": "0",
    "C_beneficio": "0",
    "C_clasificacion": "1",
    "Iva": "16",
    "HistoricPricePuch": "0,00",
    "Amount": "0,00",
    "HistoricPricePonderado": "16.739,00",
    "Unidad_empaque": "0",
    "CompositionId1": "",
    "Ptg_max_dscto": "70.0",
    "B_cambia_precio": "1",
    "Categoria": "P    ",
    "B_kit": "0",
    "B_explosion": "0",
    "B_promocion": "1",
    "Ubicacion": "0",
    "Und_medida": "1",
    "Dscto_vta": "70",
    "B_surtido": "1",
    "B_precio_max": "0",
    "Consumo": ".0",
    "Decimal1": "0",
    "Sw_serial": "0",
    "Sw_valida_max_dscto": "1",
    "Sw_Venta_Negativa": "1",
    "IdState": null
  },
  {
    "IdReference": null,
    "DataAreaId": "2",
    "C_referencia": "9271007",
    "ItemId": "PF12610118",
    "ItemName": "BLUSA ENCAJE MARIA FALACE",
    "C_proveedor": "1",
    "Dimension": "6",
    "CodLine": "7",
    "CodReference": null,
    "CodCategory": "26",
    "C_Subcategoria": "2",
    "CodSegmento": "12",
    "DivisionId": "61",
    "C_grupo_talla": "0",
    "ItemCollectionId": "325",
    "C_material": "0",
    "C_beneficio": "0",
    "C_clasificacion": "1",
    "Iva": "16",
    "HistoricPricePuch": "0,00",
    "Amount": "0,00",
    "HistoricPricePonderado": "17.219,00",
    "Unidad_empaque": "0",
    "CompositionId1": "",
    "Ptg_max_dscto": "70.0",
    "B_cambia_precio": "1",
    "Categoria": "P    ",
    "B_kit": "0",
    "B_explosion": "0",
    "B_promocion": "1",
    "Ubicacion": "0",
    "Und_medida": "1",
    "Dscto_vta": "70",
    "B_surtido": "1",
    "B_precio_max": "0",
    "Consumo": ".0",
    "Decimal1": "0",
    "Sw_serial": "0",
    "Sw_valida_max_dscto": "1",
    "Sw_Venta_Negativa": "1",
    "IdState": null
  },
  {
    "IdReference": null,
    "DataAreaId": "2",
    "C_referencia": "9271016",
    "ItemId": "PF12610119",
    "ItemName": "BLUSA MARIA CRUSH PRINT",
    "C_proveedor": "1",
    "Dimension": "6",
    "CodLine": "7",
    "CodReference": null,
    "CodCategory": "26",
    "C_Subcategoria": "2",
    "CodSegmento": "12",
    "DivisionId": "61",
    "C_grupo_talla": "0",
    "ItemCollectionId": "325",
    "C_material": "0",
    "C_beneficio": "0",
    "C_clasificacion": "1",
    "Iva": "16",
    "HistoricPricePuch": "0,00",
    "Amount": "0,00",
    "HistoricPricePonderado": "19.566,00",
    "Unidad_empaque": "0",
    "CompositionId1": "",
    "Ptg_max_dscto": "70.0",
    "B_cambia_precio": "1",
    "Categoria": "P    ",
    "B_kit": "0",
    "B_explosion": "0",
    "B_promocion": "1",
    "Ubicacion": "0",
    "Und_medida": "1",
    "Dscto_vta": "70",
    "B_surtido": "1",
    "B_precio_max": "0",
    "Consumo": ".0",
    "Decimal1": "0",
    "Sw_serial": "0",
    "Sw_valida_max_dscto": "1",
    "Sw_Venta_Negativa": "1",
    "IdState": null
  },
  {
    "IdReference": null,
    "DataAreaId": "2",
    "C_referencia": "9274659",
    "ItemId": "PF12610124",
    "ItemName": "CAMISA  MARIA GLADIUS",
    "C_proveedor": "1",
    "Dimension": "7",
    "CodLine": "7",
    "CodReference": null,
    "CodCategory": "26",
    "C_Subcategoria": "2",
    "CodSegmento": "12",
    "DivisionId": "61",
    "C_grupo_talla": "0",
    "ItemCollectionId": "325",
    "C_material": "0",
    "C_beneficio": "0",
    "C_clasificacion": "1",
    "Iva": "16",
    "HistoricPricePuch": "0,00",
    "Amount": "0,00",
    "HistoricPricePonderado": "24.405,00",
    "Unidad_empaque": "0",
    "CompositionId1": "",
    "Ptg_max_dscto": "70.0",
    "B_cambia_precio": "1",
    "Categoria": "P    ",
    "B_kit": "0",
    "B_explosion": "0",
    "B_promocion": "1",
    "Ubicacion": "0",
    "Und_medida": "1",
    "Dscto_vta": "70",
    "B_surtido": "1",
    "B_precio_max": "0",
    "Consumo": ".0",
    "Decimal1": "0",
    "Sw_serial": "0",
    "Sw_valida_max_dscto": "1",
    "Sw_Venta_Negativa": "1",
    "IdState": null
  },
  {
    "IdReference": null,
    "DataAreaId": "2",
    "C_referencia": "9274660",
    "ItemId": "PF12610125",
    "ItemName": "CAMISA MARIA MOLLI",
    "C_proveedor": "1",
    "Dimension": "7",
    "CodLine": "7",
    "CodReference": null,
    "CodCategory": "26",
    "C_Subcategoria": "2",
    "CodSegmento": "12",
    "DivisionId": "61",
    "C_grupo_talla": "0",
    "ItemCollectionId": "325",
    "C_material": "0",
    "C_beneficio": "0",
    "C_clasificacion": "1",
    "Iva": "16",
    "HistoricPricePuch": "0,00",
    "Amount": "0,00",
    "HistoricPricePonderado": "24.857,00",
    "Unidad_empaque": "0",
    "CompositionId1": "",
    "Ptg_max_dscto": "70.0",
    "B_cambia_precio": "1",
    "Categoria": "P    ",
    "B_kit": "0",
    "B_explosion": "0",
    "B_promocion": "1",
    "Ubicacion": "0",
    "Und_medida": "1",
    "Dscto_vta": "70",
    "B_surtido": "1",
    "B_precio_max": "0",
    "Consumo": ".0",
    "Decimal1": "0",
    "Sw_serial": "0",
    "Sw_valida_max_dscto": "1",
    "Sw_Venta_Negativa": "1",
    "IdState": null
  },
  {
    "IdReference": null,
    "DataAreaId": "2",
    "C_referencia": "9282514",
    "ItemId": "PF12610133",
    "ItemName": "BLUSA",
    "C_proveedor": "1",
    "Dimension": "7",
    "CodLine": "7",
    "CodReference": null,
    "CodCategory": "26",
    "C_Subcategoria": "2",
    "CodSegmento": "12",
    "DivisionId": "61",
    "C_grupo_talla": "0",
    "ItemCollectionId": "325",
    "C_material": "0",
    "C_beneficio": "0",
    "C_clasificacion": "1",
    "Iva": "16",
    "HistoricPricePuch": "0,00",
    "Amount": "0,00",
    "HistoricPricePonderado": "16.500,00",
    "Unidad_empaque": "0",
    "CompositionId1": "",
    "Ptg_max_dscto": "70.0",
    "B_cambia_precio": "1",
    "Categoria": "P    ",
    "B_kit": "0",
    "B_explosion": "0",
    "B_promocion": "1",
    "Ubicacion": "0",
    "Und_medida": "1",
    "Dscto_vta": "70",
    "B_surtido": "1",
    "B_precio_max": "0",
    "Consumo": ".0",
    "Decimal1": "0",
    "Sw_serial": "0",
    "Sw_valida_max_dscto": "1",
    "Sw_Venta_Negativa": "1",
    "IdState": null
  },
  {
    "IdReference": null,
    "DataAreaId": "2",
    "C_referencia": "9269990",
    "ItemId": "PF12620170",
    "ItemName": "CAMISETA MARIA DANNA",
    "C_proveedor": "1",
    "Dimension": "7",
    "CodLine": "0",
    "CodReference": null,
    "CodCategory": "26",
    "C_Subcategoria": "2",
    "CodSegmento": "12",
    "DivisionId": "62",
    "C_grupo_talla": "0",
    "ItemCollectionId": "325",
    "C_material": "0",
    "C_beneficio": "0",
    "C_clasificacion": "1",
    "Iva": "16",
    "HistoricPricePuch": "0,00",
    "Amount": "0,00",
    "HistoricPricePonderado": "13.727,00",
    "Unidad_empaque": "0",
    "CompositionId1": "",
    "Ptg_max_dscto": "70.0",
    "B_cambia_precio": "1",
    "Categoria": "P    ",
    "B_kit": "0",
    "B_explosion": "0",
    "B_promocion": "1",
    "Ubicacion": "0",
    "Und_medida": "1",
    "Dscto_vta": "70",
    "B_surtido": "1",
    "B_precio_max": "0",
    "Consumo": ".0",
    "Decimal1": "0",
    "Sw_serial": "0",
    "Sw_valida_max_dscto": "1",
    "Sw_Venta_Negativa": "1",
    "IdState": null
  },
  {
    "IdReference": null,
    "DataAreaId": "2",
    "C_referencia": "9270000",
    "ItemId": "PF12620171",
    "ItemName": "CAMISETA MARIA RAIN",
    "C_proveedor": "1",
    "Dimension": "7",
    "CodLine": "0",
    "CodReference": null,
    "CodCategory": "26",
    "C_Subcategoria": "2",
    "CodSegmento": "12",
    "DivisionId": "62",
    "C_grupo_talla": "0",
    "ItemCollectionId": "325",
    "C_material": "0",
    "C_beneficio": "0",
    "C_clasificacion": "1",
    "Iva": "16",
    "HistoricPricePuch": "0,00",
    "Amount": "0,00",
    "HistoricPricePonderado": "25.218,00",
    "Unidad_empaque": "0",
    "CompositionId1": "",
    "Ptg_max_dscto": "70.0",
    "B_cambia_precio": "1",
    "Categoria": "P    ",
    "B_kit": "0",
    "B_explosion": "0",
    "B_promocion": "1",
    "Ubicacion": "0",
    "Und_medida": "1",
    "Dscto_vta": "70",
    "B_surtido": "1",
    "B_precio_max": "0",
    "Consumo": ".0",
    "Decimal1": "0",
    "Sw_serial": "0",
    "Sw_valida_max_dscto": "1",
    "Sw_Venta_Negativa": "1",
    "IdState": null
  },
  {
    "IdReference": null,
    "DataAreaId": "2",
    "C_referencia": "9270001",
    "ItemId": "PF12620172",
    "ItemName": "BLUSA",
    "C_proveedor": "1",
    "Dimension": "7",
    "CodLine": "0",
    "CodReference": null,
    "CodCategory": "26",
    "C_Subcategoria": "2",
    "CodSegmento": "12",
    "DivisionId": "62",
    "C_grupo_talla": "0",
    "ItemCollectionId": "325",
    "C_material": "0",
    "C_beneficio": "0",
    "C_clasificacion": "1",
    "Iva": "16",
    "HistoricPricePuch": "0,00",
    "Amount": "0,00",
    "HistoricPricePonderado": "9.610,00",
    "Unidad_empaque": "0",
    "CompositionId1": "",
    "Ptg_max_dscto": "70.0",
    "B_cambia_precio": "1",
    "Categoria": "P    ",
    "B_kit": "0",
    "B_explosion": "0",
    "B_promocion": "1",
    "Ubicacion": "0",
    "Und_medida": "1",
    "Dscto_vta": "70",
    "B_surtido": "1",
    "B_precio_max": "0",
    "Consumo": ".0",
    "Decimal1": "0",
    "Sw_serial": "0",
    "Sw_valida_max_dscto": "1",
    "Sw_Venta_Negativa": "1",
    "IdState": null
  },
  {
    "IdReference": null,
    "DataAreaId": "2",
    "C_referencia": "9270409",
    "ItemId": "PF12620173",
    "ItemName": "C42331 BLUSA GALERY",
    "C_proveedor": "1",
    "Dimension": "7",
    "CodLine": "0",
    "CodReference": null,
    "CodCategory": "26",
    "C_Subcategoria": "2",
    "CodSegmento": "12",
    "DivisionId": "62",
    "C_grupo_talla": "0",
    "ItemCollectionId": "325",
    "C_material": "0",
    "C_beneficio": "0",
    "C_clasificacion": "1",
    "Iva": "16",
    "HistoricPricePuch": "0,00",
    "Amount": "0,00",
    "HistoricPricePonderado": "11.106,00",
    "Unidad_empaque": "0",
    "CompositionId1": "",
    "Ptg_max_dscto": "70.0",
    "B_cambia_precio": "1",
    "Categoria": "P    ",
    "B_kit": "0",
    "B_explosion": "0",
    "B_promocion": "1",
    "Ubicacion": "0",
    "Und_medida": "1",
    "Dscto_vta": "70",
    "B_surtido": "1",
    "B_precio_max": "0",
    "Consumo": ".0",
    "Decimal1": "0",
    "Sw_serial": "0",
    "Sw_valida_max_dscto": "1",
    "Sw_Venta_Negativa": "1",
    "IdState": null
  },
  {
    "IdReference": null,
    "DataAreaId": "2",
    "C_referencia": "9270424",
    "ItemId": "PF12620174",
    "ItemName": "CAMISETA MARIA FLAME",
    "C_proveedor": "1",
    "Dimension": "7",
    "CodLine": "0",
    "CodReference": null,
    "CodCategory": "26",
    "C_Subcategoria": "2",
    "CodSegmento": "12",
    "DivisionId": "62",
    "C_grupo_talla": "0",
    "ItemCollectionId": "325",
    "C_material": "0",
    "C_beneficio": "0",
    "C_clasificacion": "1",
    "Iva": "16",
    "HistoricPricePuch": "0,00",
    "Amount": "0,00",
    "HistoricPricePonderado": "10.224,00",
    "Unidad_empaque": "0",
    "CompositionId1": "",
    "Ptg_max_dscto": "70.0",
    "B_cambia_precio": "1",
    "Categoria": "P    ",
    "B_kit": "0",
    "B_explosion": "0",
    "B_promocion": "1",
    "Ubicacion": "0",
    "Und_medida": "1",
    "Dscto_vta": "70",
    "B_surtido": "1",
    "B_precio_max": "0",
    "Consumo": ".0",
    "Decimal1": "0",
    "Sw_serial": "0",
    "Sw_valida_max_dscto": "1",
    "Sw_Venta_Negativa": "1",
    "IdState": null
  },
  {
    "IdReference": null,
    "DataAreaId": "2",
    "C_referencia": "9271263",
    "ItemId": "PF12620175",
    "ItemName": "CAMISETA MARIA MUSS",
    "C_proveedor": "1",
    "Dimension": "7",
    "CodLine": "0",
    "CodReference": null,
    "CodCategory": "26",
    "C_Subcategoria": "2",
    "CodSegmento": "12",
    "DivisionId": "62",
    "C_grupo_talla": "0",
    "ItemCollectionId": "325",
    "C_material": "0",
    "C_beneficio": "0",
    "C_clasificacion": "1",
    "Iva": "16",
    "HistoricPricePuch": "0,00",
    "Amount": "0,00",
    "HistoricPricePonderado": "19.958,00",
    "Unidad_empaque": "0",
    "CompositionId1": "",
    "Ptg_max_dscto": "70.0",
    "B_cambia_precio": "1",
    "Categoria": "P    ",
    "B_kit": "0",
    "B_explosion": "0",
    "B_promocion": "1",
    "Ubicacion": "0",
    "Und_medida": "1",
    "Dscto_vta": "70",
    "B_surtido": "1",
    "B_precio_max": "0",
    "Consumo": ".0",
    "Decimal1": "0",
    "Sw_serial": "0",
    "Sw_valida_max_dscto": "1",
    "Sw_Venta_Negativa": "1",
    "IdState": null
  },
  {
    "IdReference": null,
    "DataAreaId": "2",
    "C_referencia": "9269537",
    "ItemId": "PF12710033",
    "ItemName": "PANTALON MARIA SEDOSO 2012 - MARZO",
    "C_proveedor": "1",
    "Dimension": "7",
    "CodLine": "19",
    "CodReference": null,
    "CodCategory": "26",
    "C_Subcategoria": "2",
    "CodSegmento": "12",
    "DivisionId": "71",
    "C_grupo_talla": "0",
    "ItemCollectionId": "325",
    "C_material": "0",
    "C_beneficio": "0",
    "C_clasificacion": "1",
    "Iva": "16",
    "HistoricPricePuch": "0,00",
    "Amount": "0,00",
    "HistoricPricePonderado": "31.098,00",
    "Unidad_empaque": "0",
    "CompositionId1": "",
    "Ptg_max_dscto": "70.0",
    "B_cambia_precio": "1",
    "Categoria": "P    ",
    "B_kit": "0",
    "B_explosion": "0",
    "B_promocion": "1",
    "Ubicacion": "0",
    "Und_medida": "1",
    "Dscto_vta": "70",
    "B_surtido": "1",
    "B_precio_max": "0",
    "Consumo": ".0",
    "Decimal1": "0",
    "Sw_serial": "0",
    "Sw_valida_max_dscto": "1",
    "Sw_Venta_Negativa": "1",
    "IdState": null
  },
  {
    "IdReference": null,
    "DataAreaId": "2",
    "C_referencia": "9270482",
    "ItemId": "PF12710034",
    "ItemName": "PANTALON MARIA PANDORA",
    "C_proveedor": "1",
    "Dimension": "7",
    "CodLine": "19",
    "CodReference": null,
    "CodCategory": "26",
    "C_Subcategoria": "2",
    "CodSegmento": "12",
    "DivisionId": "71",
    "C_grupo_talla": "0",
    "ItemCollectionId": "325",
    "C_material": "0",
    "C_beneficio": "0",
    "C_clasificacion": "1",
    "Iva": "16",
    "HistoricPricePuch": "0,00",
    "Amount": "0,00",
    "HistoricPricePonderado": "23.791,00",
    "Unidad_empaque": "0",
    "CompositionId1": "",
    "Ptg_max_dscto": "70.0",
    "B_cambia_precio": "1",
    "Categoria": "P    ",
    "B_kit": "0",
    "B_explosion": "0",
    "B_promocion": "1",
    "Ubicacion": "0",
    "Und_medida": "1",
    "Dscto_vta": "70",
    "B_surtido": "1",
    "B_precio_max": "0",
    "Consumo": ".0",
    "Decimal1": "0",
    "Sw_serial": "0",
    "Sw_valida_max_dscto": "1",
    "Sw_Venta_Negativa": "1",
    "IdState": null
  },
  {
    "IdReference": null,
    "DataAreaId": "2",
    "C_referencia": "9274671",
    "ItemId": "PF12710039",
    "ItemName": "PANTALON MARIA AMELIA",
    "C_proveedor": "1",
    "Dimension": "7",
    "CodLine": "19",
    "CodReference": null,
    "CodCategory": "26",
    "C_Subcategoria": "2",
    "CodSegmento": "12",
    "DivisionId": "71",
    "C_grupo_talla": "0",
    "ItemCollectionId": "325",
    "C_material": "0",
    "C_beneficio": "0",
    "C_clasificacion": "1",
    "Iva": "16",
    "HistoricPricePuch": "0,00",
    "Amount": "0,00",
    "HistoricPricePonderado": "23.428,00",
    "Unidad_empaque": "0",
    "CompositionId1": "",
    "Ptg_max_dscto": "70.0",
    "B_cambia_precio": "1",
    "Categoria": "P    ",
    "B_kit": "0",
    "B_explosion": "0",
    "B_promocion": "1",
    "Ubicacion": "0",
    "Und_medida": "1",
    "Dscto_vta": "70",
    "B_surtido": "1",
    "B_precio_max": "0",
    "Consumo": ".0",
    "Decimal1": "0",
    "Sw_serial": "0",
    "Sw_valida_max_dscto": "1",
    "Sw_Venta_Negativa": "1",
    "IdState": null
  },
  {
    "IdReference": null,
    "DataAreaId": "2",
    "C_referencia": "9272250",
    "ItemId": "PF12720020",
    "ItemName": "FALDA",
    "C_proveedor": "1",
    "Dimension": "7",
    "CodLine": "0",
    "CodReference": null,
    "CodCategory": "26",
    "C_Subcategoria": "2",
    "CodSegmento": "12",
    "DivisionId": "72",
    "C_grupo_talla": "0",
    "ItemCollectionId": "325",
    "C_material": "0",
    "C_beneficio": "0",
    "C_clasificacion": "1",
    "Iva": "16",
    "HistoricPricePuch": "0,00",
    "Amount": "0,00",
    "HistoricPricePonderado": "19.729,00",
    "Unidad_empaque": "0",
    "CompositionId1": "",
    "Ptg_max_dscto": "70.0",
    "B_cambia_precio": "1",
    "Categoria": "P    ",
    "B_kit": "0",
    "B_explosion": "0",
    "B_promocion": "1",
    "Ubicacion": "0",
    "Und_medida": "1",
    "Dscto_vta": "70",
    "B_surtido": "1",
    "B_precio_max": "0",
    "Consumo": ".0",
    "Decimal1": "0",
    "Sw_serial": "0",
    "Sw_valida_max_dscto": "1",
    "Sw_Venta_Negativa": "1",
    "IdState": null
  },
  {
    "IdReference": null,
    "DataAreaId": "2",
    "C_referencia": "9270024",
    "ItemId": "PF12740033",
    "ItemName": "SHORT MARIA PANDORA",
    "C_proveedor": "1",
    "Dimension": "6",
    "CodLine": "0",
    "CodReference": null,
    "CodCategory": "26",
    "C_Subcategoria": "2",
    "CodSegmento": "12",
    "DivisionId": "74",
    "C_grupo_talla": "0",
    "ItemCollectionId": "325",
    "C_material": "0",
    "C_beneficio": "0",
    "C_clasificacion": "1",
    "Iva": "16",
    "HistoricPricePuch": "0,00",
    "Amount": "0,00",
    "HistoricPricePonderado": "15.964,00",
    "Unidad_empaque": "0",
    "CompositionId1": "",
    "Ptg_max_dscto": "70.0",
    "B_cambia_precio": "1",
    "Categoria": "P    ",
    "B_kit": "0",
    "B_explosion": "0",
    "B_promocion": "1",
    "Ubicacion": "0",
    "Und_medida": "1",
    "Dscto_vta": "70",
    "B_surtido": "1",
    "B_precio_max": "0",
    "Consumo": ".0",
    "Decimal1": "0",
    "Sw_serial": "0",
    "Sw_valida_max_dscto": "1",
    "Sw_Venta_Negativa": "1",
    "IdState": null
  },
  {
    "IdReference": null,
    "DataAreaId": "2",
    "C_referencia": "9269991",
    "ItemId": "PF12810118",
    "ItemName": "VESTIDO MARIA MAITAI",
    "C_proveedor": "1",
    "Dimension": "7",
    "CodLine": "0",
    "CodReference": null,
    "CodCategory": "26",
    "C_Subcategoria": "2",
    "CodSegmento": "12",
    "DivisionId": "81",
    "C_grupo_talla": "0",
    "ItemCollectionId": "325",
    "C_material": "0",
    "C_beneficio": "0",
    "C_clasificacion": "1",
    "Iva": "16",
    "HistoricPricePuch": "0,00",
    "Amount": "0,00",
    "HistoricPricePonderado": "13.324,00",
    "Unidad_empaque": "0",
    "CompositionId1": "",
    "Ptg_max_dscto": "70.0",
    "B_cambia_precio": "1",
    "Categoria": "P    ",
    "B_kit": "0",
    "B_explosion": "0",
    "B_promocion": "1",
    "Ubicacion": "0",
    "Und_medida": "1",
    "Dscto_vta": "70",
    "B_surtido": "1",
    "B_precio_max": "0",
    "Consumo": ".0",
    "Decimal1": "0",
    "Sw_serial": "0",
    "Sw_valida_max_dscto": "1",
    "Sw_Venta_Negativa": "1",
    "IdState": null
  },
  {
    "IdReference": null,
    "DataAreaId": "2",
    "C_referencia": "9269992",
    "ItemId": "PF12810119",
    "ItemName": "VESTIDO MARIA PANTOJA",
    "C_proveedor": "1",
    "Dimension": "7",
    "CodLine": "0",
    "CodReference": null,
    "CodCategory": "26",
    "C_Subcategoria": "2",
    "CodSegmento": "12",
    "DivisionId": "81",
    "C_grupo_talla": "0",
    "ItemCollectionId": "325",
    "C_material": "0",
    "C_beneficio": "0",
    "C_clasificacion": "1",
    "Iva": "16",
    "HistoricPricePuch": "0,00",
    "Amount": "0,00",
    "HistoricPricePonderado": "21.589,00",
    "Unidad_empaque": "0",
    "CompositionId1": "",
    "Ptg_max_dscto": "70.0",
    "B_cambia_precio": "1",
    "Categoria": "P    ",
    "B_kit": "0",
    "B_explosion": "0",
    "B_promocion": "1",
    "Ubicacion": "0",
    "Und_medida": "1",
    "Dscto_vta": "70",
    "B_surtido": "1",
    "B_precio_max": "0",
    "Consumo": ".0",
    "Decimal1": "0",
    "Sw_serial": "0",
    "Sw_valida_max_dscto": "1",
    "Sw_Venta_Negativa": "1",
    "IdState": null
  },
  {
    "IdReference": null,
    "DataAreaId": "2",
    "C_referencia": "9270007",
    "ItemId": "PF12810120",
    "ItemName": "VESTIDO MARIA ATENEA",
    "C_proveedor": "1",
    "Dimension": "7",
    "CodLine": "0",
    "CodReference": null,
    "CodCategory": "26",
    "C_Subcategoria": "2",
    "CodSegmento": "12",
    "DivisionId": "81",
    "C_grupo_talla": "0",
    "ItemCollectionId": "325",
    "C_material": "0",
    "C_beneficio": "0",
    "C_clasificacion": "1",
    "Iva": "16",
    "HistoricPricePuch": "0,00",
    "Amount": "0,00",
    "HistoricPricePonderado": "26.828,00",
    "Unidad_empaque": "0",
    "CompositionId1": "",
    "Ptg_max_dscto": "70.0",
    "B_cambia_precio": "1",
    "Categoria": "P    ",
    "B_kit": "0",
    "B_explosion": "0",
    "B_promocion": "1",
    "Ubicacion": "0",
    "Und_medida": "1",
    "Dscto_vta": "70",
    "B_surtido": "1",
    "B_precio_max": "0",
    "Consumo": ".0",
    "Decimal1": "0",
    "Sw_serial": "0",
    "Sw_valida_max_dscto": "1",
    "Sw_Venta_Negativa": "1",
    "IdState": null
  },
  {
    "IdReference": null,
    "DataAreaId": "2",
    "C_referencia": "9270416",
    "ItemId": "PF12810121",
    "ItemName": "VESTIDO MARIA ARTEMISA",
    "C_proveedor": "1",
    "Dimension": "7",
    "CodLine": "0",
    "CodReference": null,
    "CodCategory": "26",
    "C_Subcategoria": "2",
    "CodSegmento": "12",
    "DivisionId": "81",
    "C_grupo_talla": "0",
    "ItemCollectionId": "325",
    "C_material": "0",
    "C_beneficio": "0",
    "C_clasificacion": "1",
    "Iva": "16",
    "HistoricPricePuch": "0,00",
    "Amount": "0,00",
    "HistoricPricePonderado": "19.542,00",
    "Unidad_empaque": "0",
    "CompositionId1": "",
    "Ptg_max_dscto": "70.0",
    "B_cambia_precio": "1",
    "Categoria": "P    ",
    "B_kit": "0",
    "B_explosion": "0",
    "B_promocion": "1",
    "Ubicacion": "0",
    "Und_medida": "1",
    "Dscto_vta": "70",
    "B_surtido": "1",
    "B_precio_max": "0",
    "Consumo": ".0",
    "Decimal1": "0",
    "Sw_serial": "0",
    "Sw_valida_max_dscto": "1",
    "Sw_Venta_Negativa": "1",
    "IdState": null
  },
  {
    "IdReference": null,
    "DataAreaId": "2",
    "C_referencia": "9270481",
    "ItemId": "PF12810122",
    "ItemName": "VESTIDO LARGO MARIA KALI",
    "C_proveedor": "1",
    "Dimension": "6",
    "CodLine": "0",
    "CodReference": null,
    "CodCategory": "26",
    "C_Subcategoria": "2",
    "CodSegmento": "12",
    "DivisionId": "81",
    "C_grupo_talla": "0",
    "ItemCollectionId": "325",
    "C_material": "0",
    "C_beneficio": "0",
    "C_clasificacion": "1",
    "Iva": "16",
    "HistoricPricePuch": "0,00",
    "Amount": "0,00",
    "HistoricPricePonderado": "38.471,00",
    "Unidad_empaque": "0",
    "CompositionId1": "",
    "Ptg_max_dscto": "70.0",
    "B_cambia_precio": "1",
    "Categoria": "P    ",
    "B_kit": "0",
    "B_explosion": "0",
    "B_promocion": "1",
    "Ubicacion": "0",
    "Und_medida": "1",
    "Dscto_vta": "70",
    "B_surtido": "1",
    "B_precio_max": "0",
    "Consumo": ".0",
    "Decimal1": "0",
    "Sw_serial": "0",
    "Sw_valida_max_dscto": "1",
    "Sw_Venta_Negativa": "1",
    "IdState": null
  },
  {
    "IdReference": null,
    "DataAreaId": "2",
    "C_referencia": "9270485",
    "ItemId": "PF12810123",
    "ItemName": "VESTIDO MARIA AMARETTO",
    "C_proveedor": "1",
    "Dimension": "7",
    "CodLine": "0",
    "CodReference": null,
    "CodCategory": "26",
    "C_Subcategoria": "2",
    "CodSegmento": "12",
    "DivisionId": "81",
    "C_grupo_talla": "1",
    "ItemCollectionId": "325",
    "C_material": "0",
    "C_beneficio": "0",
    "C_clasificacion": "1",
    "Iva": "16",
    "HistoricPricePuch": "0,00",
    "Amount": "0,00",
    "HistoricPricePonderado": "16.753,04",
    "Unidad_empaque": "0",
    "CompositionId1": "",
    "Ptg_max_dscto": "70.0",
    "B_cambia_precio": "1",
    "Categoria": "P    ",
    "B_kit": "0",
    "B_explosion": "0",
    "B_promocion": "1",
    "Ubicacion": "1",
    "Und_medida": "1",
    "Dscto_vta": "0",
    "B_surtido": "0",
    "B_precio_max": "0",
    "Consumo": ".0",
    "Decimal1": "0",
    "Sw_serial": "0",
    "Sw_valida_max_dscto": "1",
    "Sw_Venta_Negativa": "1",
    "IdState": null
  },
  {
    "IdReference": null,
    "DataAreaId": "2",
    "C_referencia": "9270750",
    "ItemId": "PF12810124",
    "ItemName": "VESTIDO LARGO MARIA PANTERA",
    "C_proveedor": "1",
    "Dimension": "6",
    "CodLine": "0",
    "CodReference": null,
    "CodCategory": "26",
    "C_Subcategoria": "2",
    "CodSegmento": "12",
    "DivisionId": "81",
    "C_grupo_talla": "0",
    "ItemCollectionId": "325",
    "C_material": "0",
    "C_beneficio": "0",
    "C_clasificacion": "1",
    "Iva": "16",
    "HistoricPricePuch": "0,00",
    "Amount": "0,00",
    "HistoricPricePonderado": "36.906,00",
    "Unidad_empaque": "0",
    "CompositionId1": "",
    "Ptg_max_dscto": "70.0",
    "B_cambia_precio": "1",
    "Categoria": "P    ",
    "B_kit": "0",
    "B_explosion": "0",
    "B_promocion": "1",
    "Ubicacion": "0",
    "Und_medida": "1",
    "Dscto_vta": "70",
    "B_surtido": "1",
    "B_precio_max": "0",
    "Consumo": ".0",
    "Decimal1": "0",
    "Sw_serial": "0",
    "Sw_valida_max_dscto": "1",
    "Sw_Venta_Negativa": "1",
    "IdState": null
  }
]